[{"senderKeyId":537907806,"senderChainKey":{"iteration":2729,"seed":"Zb7td2CQL2WKOJELMC8Xs7m6dXgl1dw6a0OwxLL/oYI="},"senderSigningKey":{"public":"Bfm54sweLezCa907oDtyt+aPCFd4H5FbZTVIp5zqDHh8"},"senderMessageKeys":[{},{},{},{},{},{},{},{},{},{},{},{},{},{},{},{},{},{},{},{},{},{},{},{},{},{},{},{},{},{},{},{},{},{},{},{},{},{},{},{},{},{},{},{},{},{},{},{},{},{},{},{},{},{},{},{},{},{},{},{},{},{},{},{},{},{},{},{},{},{},{},{},{},{},{},{},{},{},{},{},{},{},{},{},{},{},{},{},{},{},{},{},{},{},{},{},{},{},{},{},{},{},{},{},{},{},{},{},{},{},{},{},{},{},{},{},{},{},{},{},{},{},{},{},{},{},{},{},{},{},{},{},{},{},{},{},{},{},{},{},{},{},{},{},{},{},{},{},{},{},{},{},{},{},{},{},{},{},{},{},{},{},{},{},{},{},{},{},{},{},{},{},{},{},{},{},{},{},{},{},{},{},{},{}]},{"senderKeyId":537907806,"senderChainKey":{"iteration":2543,"seed":"PepfEGZ2iR4Vp+/mSZBF8yku/EvI4UcfoXfEXYLNV1E="},"senderSigningKey":{"public":"Bfm54sweLezCa907oDtyt+aPCFd4H5FbZTVIp5zqDHh8"},"senderMessageKeys":[]},{"senderKeyId":537907806,"senderChainKey":{"iteration":2545,"seed":"Dqma94562h65iCpJC/gngknuZTQSpv/63lwjkvfkzwE="},"senderSigningKey":{"public":"Bfm54sweLezCa907oDtyt+aPCFd4H5FbZTVIp5zqDHh8"},"senderMessageKeys":[]},{"senderKeyId":537907806,"senderChainKey":{"iteration":2711,"seed":"Baz1bKZnepvxPP+OJT+M/EgiUuJgTLBYdwhYr0KRc+c="},"senderSigningKey":{"public":"Bfm54sweLezCa907oDtyt+aPCFd4H5FbZTVIp5zqDHh8"},"senderMessageKeys":[]},{"senderKeyId":537907806,"senderChainKey":{"iteration":2713,"seed":"2jBLnwmfEGI3gfEiMl06qvXoVcEFpfAodWIN376ELDM="},"senderSigningKey":{"public":"Bfm54sweLezCa907oDtyt+aPCFd4H5FbZTVIp5zqDHh8"},"senderMessageKeys":[]}]